bentobuild/__init__.py
bentobuild/builder.py
bentobuild/job.py
bentobuild/k8s.py
tests/__init__.py
tests/test_k8s.py
bentobuild-0.0.5.dist-info/LICENSE
bentobuild-0.0.5.dist-info/METADATA
bentobuild-0.0.5.dist-info/WHEEL
bentobuild-0.0.5.dist-info/top_level.txt
bentobuild-0.0.5.dist-info/RECORD
