Metadata-Version: 2.1
Name: bentobuild
Version: 0.0.5
Summary: Build BentoML Services into Images on K8S
Home-page: https://github.com/iancoffey/bentoml-builder
Author: Ian Coffey
Author-email: icoffey@vmware.com
License: UNKNOWN
Platform: UNKNOWN
Classifier: Programming Language :: Python :: 3
Classifier: License :: OSI Approved :: MIT License
Classifier: Operating System :: OS Independent
Requires-Python: >=3.6
